hlpl_photographer/__init__.py
hlpl_photographer/__main__.py
hlpl_photographer/setup.cfg
hlpl_photographer-1.0.0.dist-info/LICENSE
hlpl_photographer-1.0.0.dist-info/METADATA
hlpl_photographer-1.0.0.dist-info/WHEEL
hlpl_photographer-1.0.0.dist-info/entry_points.txt
hlpl_photographer-1.0.0.dist-info/top_level.txt
hlpl_photographer-1.0.0.dist-info/RECORD
